MANIFEST.in
README.rst
setup.py
tornadoist/__init__.py
tornadoist/tcelerymixin.py
tornadoist/tprocessmixin.py
tornadoist.egg-info/PKG-INFO
tornadoist.egg-info/SOURCES.txt
tornadoist.egg-info/dependency_links.txt
tornadoist.egg-info/top_level.txt