Metadata-Version: 1.1
Name: tornadoist
Version: 0.5.2
Summary: mixins for tornado
Home-page: https://github.com/eguven/tornadoist.git
Author: Eren Güven
Author-email: erenguven0@gmail.com
License: Apache License, Version 2
Keywords: tornado,celery
Platform: UNKNOWN
Classifier: Development Status :: 3 - Alpha
Classifier: Programming Language :: Python :: 2.6
Classifier: Programming Language :: Python :: 2.7
Classifier: Topic :: Utilities
Classifier: License :: OSI Approved :: Apache Software License
